cosmo_wap/__init__.py
cosmo_wap/integrated.py
cosmo_wap/main.py
cosmo_wap/peak_background_bias.py
cosmo_wap/survey_params.py
cosmo_wap/bk/GR0.py
cosmo_wap/bk/GR1.py
cosmo_wap/bk/GR2.py
cosmo_wap/bk/GR_0.py
cosmo_wap/bk/GR_1.py
cosmo_wap/bk/GR_2.py
cosmo_wap/bk/PNG.py
cosmo_wap/bk/PNG_.py
cosmo_wap/bk/RR1.py
cosmo_wap/bk/RR2.py
cosmo_wap/bk/RR_1.py
cosmo_wap/bk/WA1.py
cosmo_wap/bk/WA2.py
cosmo_wap/bk/WARR.py
cosmo_wap/bk/WA_1.py
cosmo_wap/bk/WA_2.py
cosmo_wap/bk/WSGR.py
cosmo_wap/bk/__init__.py
cosmo_wap/bk/combined.py
cosmo_wap/bk/cov.py
cosmo_wap/data_library/SKAO1Data.txt
cosmo_wap/data_library/SKAO2Data.txt
cosmo_wap/data_library/k_modes.txt
cosmo_wap/data_library/snr_surveyparams.txt
cosmo_wap/forecast/__init__.py
cosmo_wap/forecast/core.py
cosmo_wap/forecast/covariances.py
cosmo_wap/forecast/forecast.py
cosmo_wap/forecast/mpi_mcmc.py
cosmo_wap/forecast/posterior.py
cosmo_wap/lib/__init__.py
cosmo_wap/lib/betas.py
cosmo_wap/lib/bk_plots.py
cosmo_wap/lib/integrate.py
cosmo_wap/lib/luminosity_funcs.py
cosmo_wap/lib/utils.py
cosmo_wap/pk/IxS_components.py
cosmo_wap/pk/PNG.py
cosmo_wap/pk/Pk_0.py
cosmo_wap/pk/Pk_WS.py
cosmo_wap/pk/Pk_WSGR.py
cosmo_wap/pk/__init__.py
cosmo_wap/pk/combined.py
cosmo_wap/pk/cov.py
cosmo_wap/pk/covWS.py
cosmo_wap/pk/covWSGR.py
cosmo_wap/pk/int.py
cosmo_wap/pk/int_components.py
cosmowap-0.5.2.dist-info/licenses/LICENSE.txt
cosmowap-0.5.2.dist-info/METADATA
cosmowap-0.5.2.dist-info/WHEEL
cosmowap-0.5.2.dist-info/top_level.txt
cosmowap-0.5.2.dist-info/RECORD
