Metadata-Version: 2.4
Name: cosmowap
Version: 0.5.2
Summary: package for computing power spectra and bispectra
Author-email: Chris Addis <c.l.j.addis@qmul.ac.uk>
License: MIT
Project-URL: homepage, https://github.com/craddis1/CosmoWAP
Classifier: Programming Language :: Python :: 3
Classifier: License :: OSI Approved :: MIT License
Classifier: Operating System :: OS Independent
Requires-Python: >=3.10
License-File: LICENSE.txt
Requires-Dist: numpy
Requires-Dist: scipy
Requires-Dist: matplotlib
Requires-Dist: tqdm
Requires-Dist: cython
Requires-Dist: classy<3.3.2.0
Requires-Dist: chainconsumer
Requires-Dist: cobaya
Dynamic: license-file
